{
    "CandyStriped":"3000",
    "3000":"CandyStriped",
    "CandyWrapped":"3001",
    "3001":"CandyWrapped",
    "CandyChocolateBall":"3002",
    "3002":"CandyChocolateBall",
    "CandyGiant":"3003",
    "3003":"CandyGiant",
    "CandyHardCurrencyX20OAP":"3090",
    "3090":"CandyHardCurrencyX20OAP",
    "CandyHardCurrencyX100OAP":"3091",
    "3091":"CandyHardCurrencyX100OAP",
    "CandyExtraTime":"3100",
    "3100":"CandyExtraTime",
    "CandyColorBomb":"3101",
    "3101":"CandyColorBomb",
    "CandyExtraMoves":"3102",
    "3102":"CandyExtraMoves",
    "CandyColorRemove":"3103",
    "3103":"CandyColorRemove",
    "CandyComboHelper":"3104",
    "3104":"CandyComboHelper",
    "CandyHammer":"3105",
    "3105":"CandyHammer",
    "CandySwedishFish":"3106",
    "3106":"CandySwedishFish",
    "CandyDoubleScores":"3107",
    "3107":"CandyDoubleScores",
    "CandyCoconutLiquorice":"3108",
    "3108":"CandyCoconutLiquorice",
    "CandyMarshmallow":"3109",
    "3109":"CandyMarshmallow",
    "CandyShuffle":"3110",
    "3110":"CandyShuffle",
    "CandySugarDusting":"3111",
    "3111":"CandySugarDusting",
    "CandyDoubleScoresSuper":"3112",
    "3112":"CandyDoubleScoresSuper",
    "CandyRainbow":"3113",
    "3113":"CandyRainbow",
    "CandyHintBasic":"3114",
    "3114":"CandyHintBasic",
    "CandyExtraMovesPercent":"3115",
    "3115":"CandyExtraMovesPercent",
    "CandyShuffleSpecial":"3116",
    "3116":"CandyShuffleSpecial",
    "CandySweetener":"3117",
    "3117":"CandySweetener",
    "CandyFreeSwitch":"3118",
    "3118":"CandyFreeSwitch",
    "CandyExtraMovesPostGame":"3119",
    "3119":"CandyExtraMovesPostGame",
    "CandyAntiPeppar":"3120",
    "3120":"CandyAntiPeppar",
    "CandyAntiPepparPostGame":"3121",
    "3121":"CandyAntiPepparPostGame",
    "CandyStripedWrapped":"3122",
    "3122":"CandyStripedWrapped",
    "CandyExtraTimePostGame":"3123",
    "3123":"CandyExtraTimePostGame",
    "CandyJoker":"3124",
    "3124":"CandyJoker",
    "CandySweetTeeth":"3125",
    "3125":"CandySweetTeeth",
    "CandyEGSColorBomb":"3126",
    "3126":"CandyEGSColorBomb",
    "CandyEGSHammer":"3127",
    "3127":"CandyEGSHammer",
    "CandyEGSSwedishFish":"3128",
    "3128":"CandyEGSSwedishFish",
    "CandyEGSWrapped":"3129",
    "3129":"CandyEGSWrapped",
    "CandyEGSStriped":"3130",
    "3130":"CandyEGSStriped",
    "CandyEGSStripedWrapped":"3131",
    "3131":"CandyEGSStripedWrapped",
    "CandyEGSJoker":"3132",
    "3132":"CandyEGSJoker",
    "CandyEGSCoconutLiquorice":"3133",
    "3133":"CandyEGSCoconutLiquorice",
    "CandyBubbleGum":"3134",
    "3134":"CandyBubbleGum",
    "CandyEGSExtraMovesOnePack":"3221",
    "3221":"CandyEGSExtraMovesOnePack",
    "CandyEGSExtraTimeOnePack":"3222",
    "3222":"CandyEGSExtraTimeOnePack",
    "CandyEGSAntiPepparOnePack":"3223",
    "3223":"CandyEGSAntiPepparOnePack",
    "CandyPiggyBank1":"3224",
    "3224":"CandyPiggyBank1",
    "CandyPiggyBank2":"3225",
    "3225":"CandyPiggyBank2",
    "CandyPiggyBank3":"3226",
    "3226":"CandyPiggyBank3",
    "CandyMoonStruck":"3318",
    "3318":"CandyMoonStruck",
    "CandyUnlimitedLife2Hours":"3643",
    "3643":"CandyUnlimitedLife2Hours",
    "CandyUnlimitedLife6Hours":"3644",
    "3644":"CandyUnlimitedLife6Hours",
    "CandyUnlimitedLife24Hours":"3645",
    "3645":"CandyUnlimitedLife24Hours",
    "CandyUnlimitedLife1Second":"3646",
    "3646":"CandyUnlimitedLife1Second",
    "CandyColorBomb1Second":"3647",
    "3647":"CandyColorBomb1Second",
    "CandyStripedWrapped1Second":"3648",
    "3648":"CandyStripedWrapped1Second",
    "CandySwedishFish1Second":"3649",
    "3649":"CandySwedishFish1Second",
    "CandyCoconutWheel1Second":"3650",
    "3650":"CandyCoconutWheel1Second",
    "CandyJoker1Second":"3651",
    "3651":"CandyJoker1Second",
    "CandyStriped1Second":"3652",
    "3652":"CandyStriped1Second",
    "CandyWrapped1Second":"3653",
    "3653":"CandyWrapped1Second",
    "CandyColorBomb1Minute":"3654",
    "3654":"CandyColorBomb1Minute",
    "CandyStripedWrapped1Minute":"3655",
    "3655":"CandyStripedWrapped1Minute",
    "CandySwedishFish1Minute":"3656",
    "3656":"CandySwedishFish1Minute",
    "CandyCoconutWheel1Minute":"3657",
    "3657":"CandyCoconutWheel1Minute",
    "CandyJoker1Minute":"3658",
    "3658":"CandyJoker1Minute",
    "CandyStriped1Minute":"3659",
    "3659":"CandyStriped1Minute",
    "CandyWrapped1Minute":"3660",
    "3660":"CandyWrapped1Minute",
    "CandyColorBombSixPack":"3135",
    "3135":"CandyColorBombSixPack",
    "CandySwedishFishSixPack":"3136",
    "3136":"CandySwedishFishSixPack",
    "CandyFreeSwitchSixPack":"3137",
    "3137":"CandyFreeSwitchSixPack",
    "CandyHammerSixPack":"3138",
    "3138":"CandyHammerSixPack",
    "CandyColorBombTwelvePack":"3139",
    "3139":"CandyColorBombTwelvePack",
    "CandySwedishFishTwelvePack":"3140",
    "3140":"CandySwedishFishTwelvePack",
    "CandyFreeSwitchTwelvePack":"3141",
    "3141":"CandyFreeSwitchTwelvePack",
    "CandyHammerTwelvePack":"3142",
    "3142":"CandyHammerTwelvePack",
    "CandySweetTeethSixPack":"3600",
    "3600":"CandySweetTeethSixPack",
    "CandyMoonStruckSixPack":"3319",
    "3319":"CandyMoonStruckSixPack",
    "CandyAntiPepparNinePack":"3143",
    "3143":"CandyAntiPepparNinePack",
    "CandyExtraTimeNinePack":"3144",
    "3144":"CandyExtraTimeNinePack",
    "CandyJokerNinePack":"3145",
    "3145":"CandyJokerNinePack",
    "CandyCoconutLiquoriceNinePack":"3146",
    "3146":"CandyCoconutLiquoriceNinePack",
    "CandyColorBombNinePack":"3147",
    "3147":"CandyColorBombNinePack",
    "CandyHammerNinePack":"3148",
    "3148":"CandyHammerNinePack",
    "CandyStripedWrappedNinePack":"3149",
    "3149":"CandyStripedWrappedNinePack",
    "CandySwedishFishNinePack":"3150",
    "3150":"CandySwedishFishNinePack",
    "CandyFreeSwitchNinePack":"3151",
    "3151":"CandyFreeSwitchNinePack",
    "CandyBubbleGumNinePack":"3169",
    "3169":"CandyBubbleGumNinePack",
    "CandySweetTeethNinePack":"3601",
    "3601":"CandySweetTeethNinePack",
    "CandyMoonStruckNinePack":"3603",
    "3603":"CandyMoonStruckNinePack",
    "CandyColorBombElevenPack":"3602",
    "3602":"CandyColorBombElevenPack",
    "CandyAntiPepparEighteenPack":"3152",
    "3152":"CandyAntiPepparEighteenPack",
    "CandyExtraTimeEighteenPack":"3153",
    "3153":"CandyExtraTimeEighteenPack",
    "CandyJokerEighteenPack":"3154",
    "3154":"CandyJokerEighteenPack",
    "CandyCoconutLiquoriceEighteenPack":"3155",
    "3155":"CandyCoconutLiquoriceEighteenPack",
    "CandyColorBombEighteenPack":"3156",
    "3156":"CandyColorBombEighteenPack",
    "CandyHammerEighteenPack":"3157",
    "3157":"CandyHammerEighteenPack",
    "CandyStripedWrappedEighteenPack":"3158",
    "3158":"CandyStripedWrappedEighteenPack",
    "CandySwedishFishEighteenPack":"3159",
    "3159":"CandySwedishFishEighteenPack",
    "CandyFreeSwitchEighteenPack":"3160",
    "3160":"CandyFreeSwitchEighteenPack",
    "CandyBubbleGumEighteenPack":"3170",
    "3170":"CandyBubbleGumEighteenPack",
    "CandyExtraTimeEightPack":"3161",
    "3161":"CandyExtraTimeEightPack",
    "CandyJokerEightPack":"3162",
    "3162":"CandyJokerEightPack",
    "CandyCoconutLiquoriceEightPack":"3163",
    "3163":"CandyCoconutLiquoriceEightPack",
    "CandyColorBombEightPack":"3164",
    "3164":"CandyColorBombEightPack",
    "CandyExtraTimeFourteenPack":"3165",
    "3165":"CandyExtraTimeFourteenPack",
    "CandyJokerFourteenPack":"3166",
    "3166":"CandyJokerFourteenPack",
    "CandyCoconutLiquoriceFourteenPack":"3167",
    "3167":"CandyCoconutLiquoriceFourteenPack",
    "CandyColorBombFourteenPack":"3168",
    "3168":"CandyColorBombFourteenPack",
    "CandyWheelOfBoosterJackpot":"3171",
    "3171":"CandyWheelOfBoosterJackpot",
    "CandyWheelOfBoosterSpin":"3205",
    "3205":"CandyWheelOfBoosterSpin",
    "CandyWheelOfBoosterSpin2":"3206",
    "3206":"CandyWheelOfBoosterSpin2",
    "CandyEGPWheelOfBoosterSpin":"3214",
    "3214":"CandyEGPWheelOfBoosterSpin",
    "CandyEGSExtraMovesFivePack":"3172",
    "3172":"CandyEGSExtraMovesFivePack",
    "CandyEGSExtraMovesFifteenPack":"3173",
    "3173":"CandyEGSExtraMovesFifteenPack",
    "CandyEGSExtraMovesFiftyPack":"3174",
    "3174":"CandyEGSExtraMovesFiftyPack",
    "CandyEGSAntiPepparFivePack":"3175",
    "3175":"CandyEGSAntiPepparFivePack",
    "CandyEGSAntiPepparTenPack":"3176",
    "3176":"CandyEGSAntiPepparTenPack",
    "CandyEGSAntiPepparFifteenPack":"3177",
    "3177":"CandyEGSAntiPepparFifteenPack",
    "CandyEGSAntiPepparFiftyPack":"3178",
    "3178":"CandyEGSAntiPepparFiftyPack",
    "CandyEGSExtraTimeFifteenPack":"3179",
    "3179":"CandyEGSExtraTimeFifteenPack",
    "CandyEGSExtraTimeThirtyPack":"3180",
    "3180":"CandyEGSExtraTimeThirtyPack",
    "CandyEGSExtraTimeSixtyPack":"3181",
    "3181":"CandyEGSExtraTimeSixtyPack",
    "CandyHammerOnePack":"3182",
    "3182":"CandyHammerOnePack",
    "CandySwedishFishOnePack":"3183",
    "3183":"CandySwedishFishOnePack",
    "CandyFreeSwitchOnePack":"3184",
    "3184":"CandyFreeSwitchOnePack",
    "CandyColorBombOnePack":"3185",
    "3185":"CandyColorBombOnePack",
    "CandyCoconutLiquoriceOnePack":"3186",
    "3186":"CandyCoconutLiquoriceOnePack",
    "CandyStripedWrappedOnePack":"3187",
    "3187":"CandyStripedWrappedOnePack",
    "CandyJokerOnePack":"3188",
    "3188":"CandyJokerOnePack",
    "CandyAntiPepparOnePack":"3191",
    "3191":"CandyAntiPepparOnePack",
    "CandyExtraTimeOnePack":"3192",
    "3192":"CandyExtraTimeOnePack",
    "CandyBubbleGumOnePack":"3193",
    "3193":"CandyBubbleGumOnePack",
    "CandySweetTeethOnePack":"3194",
    "3194":"CandySweetTeethOnePack",
    "CandyMoonstruckOnePack":"3197",
    "3197":"CandyMoonstruckOnePack",
    "CandyBalanceModeResetPostGame":"3189",
    "3189":"CandyBalanceModeResetPostGame",
    "CandyEGSLunarRewinder":"3190",
    "3190":"CandyEGSLunarRewinder",
    "CandyEGSLunarFreeze":"3195",
    "3195":"CandyEGSLunarFreeze",
    "CandyCharmOfExtraLife":"3200",
    "3200":"CandyCharmOfExtraLife",
    "CandyCharmOfStripedCandy":"3201",
    "3201":"CandyCharmOfStripedCandy",
    "CandyCharmOfFrozenTime":"3202",
    "3202":"CandyCharmOfFrozenTime",
    "CandyCharmOfGoldenTicket":"3203",
    "3203":"CandyCharmOfGoldenTicket",
    "CandyCharmOfGoldenTicket2":"3207",
    "3207":"CandyCharmOfGoldenTicket2",
    "CandyGoldenTicket":"3204",
    "3204":"CandyGoldenTicket",
    "CandyUnlockLevel3Friends":"3250",
    "3250":"CandyUnlockLevel3Friends",
    "CandyUnlockLevel2Friends":"3251",
    "3251":"CandyUnlockLevel2Friends",
    "CandyUnlockLevel1Friend":"3252",
    "3252":"CandyUnlockLevel1Friend",
    "CandyUnlockLevelNonPayingPlayerPromotion":"3253",
    "3253":"CandyUnlockLevelNonPayingPlayerPromotion",
    "CandyUnlockTicketLevel3Friends":"3254",
    "3254":"CandyUnlockTicketLevel3Friends",
    "CandyUnlockTicketLevel2Friends":"3255",
    "3255":"CandyUnlockTicketLevel2Friends",
    "CandyUnlockTicketLevel1Friend":"3256",
    "3256":"CandyUnlockTicketLevel1Friend",
    "CandyPartyBooster":"3257",
    "3257":"CandyPartyBooster",
    "CandyFullLife":"3260",
    "3260":"CandyFullLife",
    "CandyOneLife":"3261",
    "3261":"CandyOneLife",
    "CandySeasonPack":"3270",
    "3270":"CandySeasonPack",
    "CandyHardCurrencyX150":"3271",
    "3271":"CandyHardCurrencyX150",
    "CandyHardCurrencyX250ForMemorial":"3272",
    "3272":"CandyHardCurrencyX250ForMemorial",
    "CandyHardCurrencyX20ForMemorial":"3262",
    "3262":"CandyHardCurrencyX20ForMemorial",
    "CandyHardCurrencyX50ForMemorial":"3263",
    "3263":"CandyHardCurrencyX50ForMemorial",
    "CandyHardCurrencyX100ForMemorial":"3264",
    "3264":"CandyHardCurrencyX100ForMemorial",
    "CandyHardCurrencyX20ForChristmas":"3265",
    "3265":"CandyHardCurrencyX20ForChristmas",
    "CandyHardCurrencyX50ForChristmas":"3266",
    "3266":"CandyHardCurrencyX50ForChristmas",
    "CandyHardCurrencyX10ForSale":"3267",
    "3267":"CandyHardCurrencyX10ForSale",
    "CandyHardCurrencyX50ForSale":"3268",
    "3268":"CandyHardCurrencyX50ForSale",
    "CandyHardCurrencyX70ForSale":"3273",
    "3273":"CandyHardCurrencyX70ForSale",
    "CandyHardCurrencyX100ForSale":"3274",
    "3274":"CandyHardCurrencyX100ForSale",
    "CandyHardCurrencyX125ForSale":"3275",
    "3275":"CandyHardCurrencyX125ForSale",
    "CandyHardCurrencyX150ForSale":"3276",
    "3276":"CandyHardCurrencyX150ForSale",
    "CandyHardCurrencyX200ForSale":"3277",
    "3277":"CandyHardCurrencyX200ForSale",
    "CandyHardCurrencyX250ForSale":"3278",
    "3278":"CandyHardCurrencyX250ForSale",
    "CandyHardCurrencyX300ForSale":"3279",
    "3279":"CandyHardCurrencyX300ForSale",
    "CandyHardCurrencyX500ForSale":"3375",
    "3375":"CandyHardCurrencyX500ForSale",
    "CandyHardCurrencyX600ForSale":"3376",
    "3376":"CandyHardCurrencyX600ForSale",
    "CandyHardCurrencyX800ForSale":"3377",
    "3377":"CandyHardCurrencyX800ForSale",
    "CandyHardCurrencyX1000ForSale":"3378",
    "3378":"CandyHardCurrencyX1000ForSale",
    "CandyHardCurrencyX15Alternative":"3379",
    "3379":"CandyHardCurrencyX15Alternative",
    "CandyHardCurrencyX50Alternative":"3380",
    "3380":"CandyHardCurrencyX50Alternative",
    "CandyHardCurrencyX250Alternative":"3381",
    "3381":"CandyHardCurrencyX250Alternative",
    "CandyHardCurrencyX1000Alternative":"3382",
    "3382":"CandyHardCurrencyX1000Alternative",
    "CandyHardCurrencyX10ForSaleAlternative":"3383",
    "3383":"CandyHardCurrencyX10ForSaleAlternative",
    "CandyQuantifiedHardCurrency":"3789",
    "3789":"CandyQuantifiedHardCurrency",
    "CandyQuantifiedHardCurrencyWithBonus":"3790",
    "3790":"CandyQuantifiedHardCurrencyWithBonus",
    "CandyHardCurrency":"3280",
    "3280":"CandyHardCurrency",
    "CandyHardCurrency_TENCENT_ANDROID":"328011",
    "328011":"CandyHardCurrency_TENCENT_ANDROID",
    "CandyHardCurrency_TENCENT_IOS":"328012",
    "328012":"CandyHardCurrency_TENCENT_IOS",
    "CandyHardCurrencyX1":"3281",
    "3281":"CandyHardCurrencyX1",
    "CandyHardCurrencyX2":"3282",
    "3282":"CandyHardCurrencyX2",
    "CandyHardCurrencyX3":"3283",
    "3283":"CandyHardCurrencyX3",
    "CandyHardCurrencyX9":"3284",
    "3284":"CandyHardCurrencyX9",
    "CandyHardCurrencyX10":"3285",
    "3285":"CandyHardCurrencyX10",
    "CandyHardCurrencyX12":"3286",
    "3286":"CandyHardCurrencyX12",
    "CandyHardCurrencyX19":"3287",
    "3287":"CandyHardCurrencyX19",
    "CandyHardCurrencyX25":"3288",
    "3288":"CandyHardCurrencyX25",
    "CandyHardCurrencyX29":"3289",
    "3289":"CandyHardCurrencyX29",
    "CandyHardCurrencyX39":"3290",
    "3290":"CandyHardCurrencyX39",
    "CandyHardCurrencyX50":"3291",
    "3291":"CandyHardCurrencyX50",
    "CandyHardCurrencyX100":"3292",
    "3292":"CandyHardCurrencyX100",
    "CandyHardCurrencyX200":"3293",
    "3293":"CandyHardCurrencyX200",
    "CandyHardCurrencyX500":"3294",
    "3294":"CandyHardCurrencyX500",
    "CandyHardCurrencyX1000":"3295",
    "3295":"CandyHardCurrencyX1000",
    "CandyHardCurrencyX70":"3369",
    "3369":"CandyHardCurrencyX70",
    "CandyHardCurrencyX125":"3370",
    "3370":"CandyHardCurrencyX125",
    "CandyHardCurrencyX300":"3371",
    "3371":"CandyHardCurrencyX300",
    "CandyHardCurrencyX600":"3372",
    "3372":"CandyHardCurrencyX600",
    "CandyHardCurrencyX800":"3373",
    "3373":"CandyHardCurrencyX800",
    "CandyHardCurrencyX9ABPricingTestCase1":"3350",
    "3350":"CandyHardCurrencyX9ABPricingTestCase1",
    "CandyHardCurrencyX45ABPricingTestCase1":"3351",
    "3351":"CandyHardCurrencyX45ABPricingTestCase1",
    "CandyHardCurrencyX100ABPricingTestCase1":"3352",
    "3352":"CandyHardCurrencyX100ABPricingTestCase1",
    "CandyHardCurrencyX150ABPricingTestCase1":"3353",
    "3353":"CandyHardCurrencyX150ABPricingTestCase1",
    "CandyHardCurrencyX200ABPricingTestCase1":"3354",
    "3354":"CandyHardCurrencyX200ABPricingTestCase1",
    "CandyHardCurrencyX250ABPricingTestCase1":"3355",
    "3355":"CandyHardCurrencyX250ABPricingTestCase1",
    "CandyHardCurrencyX500ABPricingTestCase1":"3356",
    "3356":"CandyHardCurrencyX500ABPricingTestCase1",
    "CandyHardCurrencyX1000ABPricingTestCase1":"3357",
    "3357":"CandyHardCurrencyX1000ABPricingTestCase1",
    "CandyHardCurrencyX9FBGiftCard":"3358",
    "3358":"CandyHardCurrencyX9FBGiftCard",
    "CandyHardCurrencyX45FBGiftCard":"3359",
    "3359":"CandyHardCurrencyX45FBGiftCard",
    "CandyHardCurrencyX100FBGiftCard":"3360",
    "3360":"CandyHardCurrencyX100FBGiftCard",
    "CandyHardCurrencyX150FBGiftCard":"3361",
    "3361":"CandyHardCurrencyX150FBGiftCard",
    "CandyHardCurrencyX200FBGiftCard":"3362",
    "3362":"CandyHardCurrencyX200FBGiftCard",
    "CandyHardCurrencyX250FBGiftCard":"3363",
    "3363":"CandyHardCurrencyX250FBGiftCard",
    "CandyHardCurrencyX500FBGiftCard":"3364",
    "3364":"CandyHardCurrencyX500FBGiftCard",
    "CandyHardCurrencyX100ForGoldenTicketBundle":"3367",
    "3367":"CandyHardCurrencyX100ForGoldenTicketBundle",
    "CandyStarterPack100":"3365",
    "3365":"CandyStarterPack100",
    "CandyStarterPack50WithBoosters":"3366",
    "3366":"CandyStarterPack50WithBoosters",
    "CandyStarterPack50WithBoostersHigherPrice":"3368",
    "3368":"CandyStarterPack50WithBoostersHigherPrice",
    "CandyStarterPack10WithBoosters":"3374",
    "3374":"CandyStarterPack10WithBoosters",
    "CandyHardCurrencyX20":"3296",
    "3296":"CandyHardCurrencyX20",
    "CandyHardCurrencyX30":"3297",
    "3297":"CandyHardCurrencyX30",
    "CandyHardCurrencyX40":"3298",
    "3298":"CandyHardCurrencyX40",
    "CandyCoconutLiquoriceSixPack":"3208",
    "3208":"CandyCoconutLiquoriceSixPack",
    "CandyStripedWrappedSixPack":"3209",
    "3209":"CandyStripedWrappedSixPack",
    "CandyJokerSixPack":"3210",
    "3210":"CandyJokerSixPack",
    "CandyMoonstruckEighteenPack":"3213",
    "3213":"CandyMoonstruckEighteenPack",
    "CandyStripedBrush":"3240",
    "3240":"CandyStripedBrush",
    "CandyUfoIngame":"3241",
    "3241":"CandyUfoIngame",
    "CandyUfoPregameThreePack":"3242",
    "3242":"CandyUfoPregameThreePack",
    "CandyUfoPregameSixPack":"3243",
    "3243":"CandyUfoPregameSixPack",
    "CandyUfoPregameNinePack":"3244",
    "3244":"CandyUfoPregameNinePack",
    "CandyUfoIngameThreePack":"3245",
    "3245":"CandyUfoIngameThreePack",
    "CandyUfoIngameSixPack":"3246",
    "3246":"CandyUfoIngameSixPack",
    "CandyUfoIngameNinePack":"3247",
    "3247":"CandyUfoIngameNinePack",
    "CandyRandomPreGameBooster":"3248",
    "3248":"CandyRandomPreGameBooster",
    "CandyHardCurrencyX15":"3249",
    "3249":"CandyHardCurrencyX15",
    "CandyColorBombTwoPack":"3004",
    "3004":"CandyColorBombTwoPack",
    "CandyColorBombFourPack":"3005",
    "3005":"CandyColorBombFourPack",
    "CandyColorBombFivePack":"3006",
    "3006":"CandyColorBombFivePack",
    "CandyStripedWrappedTwoPack":"3007",
    "3007":"CandyStripedWrappedTwoPack",
    "CandyHammerTwoPack":"3008",
    "3008":"CandyHammerTwoPack",
    "CandyHardCurrencyX250":"3299",
    "3299":"CandyHardCurrencyX250"
}